aanft/__init__.py
aanft/aanft.py
aanft-0.1.10.dist-info/METADATA
aanft-0.1.10.dist-info/WHEEL
aanft-0.1.10.dist-info/top_level.txt
aanft-0.1.10.dist-info/RECORD
