Metadata-Version: 2.1
Name: aanft
Version: 0.1.10
Summary: Fetching WAX AtomicAssets made easier
Home-page: https://github.com/funkaclau
Author: funkaclau
Requires-Dist: aiofiles
Requires-Dist: aiohttp
Requires-Dist: asyncio
Requires-Dist: loguru
Requires-Dist: typing
Requires-Dist: typing-extensions
